oneshot_channel/__init__.py
oneshot_channel/py.typed
babichjacob_oneshot_channel-0.3.0.dist-info/WHEEL
babichjacob_oneshot_channel-0.3.0.dist-info/METADATA
babichjacob_oneshot_channel-0.3.0.dist-info/RECORD
